math2/__init__.py
math22/__init__.py
math22-2.2.dist-info/METADATA
math22-2.2.dist-info/WHEEL
math22-2.2.dist-info/top_level.txt
math22-2.2.dist-info/RECORD
