Metadata-Version: 2.1
Name: math22
Version: 2.2
Summary: useful math functions
Home-page: https://baidu.com
Author: math22
Author-email: 2691475984@qq.com
License: UNKNOWN
Platform: UNKNOWN
Classifier: Programming Language :: Python :: 3.6
Classifier: Programming Language :: Python :: 3.7
Classifier: Programming Language :: Python :: 3.8
Classifier: License :: OSI Approved :: MIT License
Classifier: Operating System :: OS Independent
